{
  "project_info": {
    "project_number": "633082908854",
    "firebase_url": "https://androidfood-55026.firebaseio.com",
    "project_id": "androidfood-55026",
    "storage_bucket": "androidfood-55026.appspot.com"
  },
  "client": [
    {
      "client_info": {
        "mobilesdk_app_id": "1:633082908854:android:202c0b5f7f154435",
        "android_client_info": {
          "package_name": "agency.techstar.food"
        }
      },
      "oauth_client": [
        {
          "client_id": "633082908854-bprt8htc8a8f9uu7d4upldi20pab2hrs.apps.googleusercontent.com",
          "client_type": 1,
          "android_info": {
            "package_name": "agency.techstar.food",
            "certificate_hash": "a0ef080e87ee397ea28e9c06f7f41381c7a6bf65"
          }
        },
        {
          "client_id": "633082908854-7v3s0tjbg22de8e4p2iemfq8uabac4d9.apps.googleusercontent.com",
          "client_type": 3
        }
      ],
      "api_key": [
        {
          "current_key": "AIzaSyBU5EbYt-OeVemPEbEhLWyUK_Dt7taWFL8"
        }
      ],
      "services": {
        "analytics_service": {
          "status": 1
        },
        "appinvite_service": {
          "status": 2,
          "other_platform_oauth_client": [
            {
              "client_id": "633082908854-7v3s0tjbg22de8e4p2iemfq8uabac4d9.apps.googleusercontent.com",
              "client_type": 3
            }
          ]
        },
        "ads_service": {
          "status": 2
        }
      }
    }
  ],
  "configuration_version": "1"
}